{
    "uid": "f9a3b67f-0efc-4601-9ead-a7e5a36d324b",
    "name": "3_Default_CatBoost",
    "preprocessing": [
        {
            "scale_y": {
                "scale": [
                    0.45249857180032577
                ],
                "mean": [
                    1.6337926329922432
                ],
                "var": [
                    0.20475495748133457
                ],
                "n_samples_seen": 35648,
                "n_features_in": 1,
                "columns": [
                    "target"
                ],
                "scale_method": "scale_normal"
            },
            "ml_task": "regression",
            "params": {
                "columns_preprocessing": {},
                "target_preprocessing": [
                    "na_exclude",
                    "scale_normal"
                ],
                "ml_task": "regression"
            }
        },
        {
            "scale_y": {
                "scale": [
                    0.452728320121102
                ],
                "mean": [
                    1.6338196106028458
                ],
                "var": [
                    0.20496293183967498
                ],
                "n_samples_seen": 35648,
                "n_features_in": 1,
                "columns": [
                    "target"
                ],
                "scale_method": "scale_normal"
            },
            "ml_task": "regression",
            "params": {
                "columns_preprocessing": {},
                "target_preprocessing": [
                    "na_exclude",
                    "scale_normal"
                ],
                "ml_task": "regression"
            }
        },
        {
            "scale_y": {
                "scale": [
                    0.4517831270663278
                ],
                "mean": [
                    1.6327985305259922
                ],
                "var": [
                    0.20410799390182965
                ],
                "n_samples_seen": 35648,
                "n_features_in": 1,
                "columns": [
                    "target"
                ],
                "scale_method": "scale_normal"
            },
            "ml_task": "regression",
            "params": {
                "columns_preprocessing": {},
                "target_preprocessing": [
                    "na_exclude",
                    "scale_normal"
                ],
                "ml_task": "regression"
            }
        },
        {
            "scale_y": {
                "scale": [
                    0.4531943738710595
                ],
                "mean": [
                    1.63323197828424
                ],
                "var": [
                    0.20538514050838164
                ],
                "n_samples_seen": 35648,
                "n_features_in": 1,
                "columns": [
                    "target"
                ],
                "scale_method": "scale_normal"
            },
            "ml_task": "regression",
            "params": {
                "columns_preprocessing": {},
                "target_preprocessing": [
                    "na_exclude",
                    "scale_normal"
                ],
                "ml_task": "regression"
            }
        },
        {
            "scale_y": {
                "scale": [
                    0.4535113664926617
                ],
                "mean": [
                    1.6337483056097843
                ],
                "var": [
                    0.2056725595380413
                ],
                "n_samples_seen": 35648,
                "n_features_in": 1,
                "columns": [
                    "target"
                ],
                "scale_method": "scale_normal"
            },
            "ml_task": "regression",
            "params": {
                "columns_preprocessing": {},
                "target_preprocessing": [
                    "na_exclude",
                    "scale_normal"
                ],
                "ml_task": "regression"
            }
        },
        {
            "scale_y": {
                "scale": [
                    0.4525530893861193
                ],
                "mean": [
                    1.6343549838443812
                ],
                "var": [
                    0.20480429871292088
                ],
                "n_samples_seen": 35648,
                "n_features_in": 1,
                "columns": [
                    "target"
                ],
                "scale_method": "scale_normal"
            },
            "ml_task": "regression",
            "params": {
                "columns_preprocessing": {},
                "target_preprocessing": [
                    "na_exclude",
                    "scale_normal"
                ],
                "ml_task": "regression"
            }
        },
        {
            "scale_y": {
                "scale": [
                    0.45324895160715173
                ],
                "mean": [
                    1.6331054604529673
                ],
                "var": [
                    0.20543461213298217
                ],
                "n_samples_seen": 35648,
                "n_features_in": 1,
                "columns": [
                    "target"
                ],
                "scale_method": "scale_normal"
            },
            "ml_task": "regression",
            "params": {
                "columns_preprocessing": {},
                "target_preprocessing": [
                    "na_exclude",
                    "scale_normal"
                ],
                "ml_task": "regression"
            }
        },
        {
            "scale_y": {
                "scale": [
                    0.45229284690378996
                ],
                "mean": [
                    1.633156009329296
                ],
                "var": [
                    0.20456881936033516
                ],
                "n_samples_seen": 35648,
                "n_features_in": 1,
                "columns": [
                    "target"
                ],
                "scale_method": "scale_normal"
            },
            "ml_task": "regression",
            "params": {
                "columns_preprocessing": {},
                "target_preprocessing": [
                    "na_exclude",
                    "scale_normal"
                ],
                "ml_task": "regression"
            }
        },
        {
            "scale_y": {
                "scale": [
                    0.45365448778038725
                ],
                "mean": [
                    1.635341350922002
                ],
                "var": [
                    0.2058023942832855
                ],
                "n_samples_seen": 35648,
                "n_features_in": 1,
                "columns": [
                    "target"
                ],
                "scale_method": "scale_normal"
            },
            "ml_task": "regression",
            "params": {
                "columns_preprocessing": {},
                "target_preprocessing": [
                    "na_exclude",
                    "scale_normal"
                ],
                "ml_task": "regression"
            }
        },
        {
            "scale_y": {
                "scale": [
                    0.45317406131288956
                ],
                "mean": [
                    1.6336192593257077
                ],
                "var": [
                    0.20536672984681859
                ],
                "n_samples_seen": 35649,
                "n_features_in": 1,
                "columns": [
                    "target"
                ],
                "scale_method": "scale_normal"
            },
            "ml_task": "regression",
            "params": {
                "columns_preprocessing": {},
                "target_preprocessing": [
                    "na_exclude",
                    "scale_normal"
                ],
                "ml_task": "regression"
            }
        }
    ],
    "learners": [
        {
            "library_version": "1.2.2",
            "algorithm_name": "CatBoost",
            "algorithm_short_name": "CatBoost",
            "uid": "c11cfce1-93c1-446d-a618-d5c127243d73",
            "params": {
                "model_type": "CatBoost",
                "ml_task": "regression",
                "n_jobs": -1,
                "learning_rate": 0.1,
                "depth": 6,
                "rsm": 1,
                "loss_function": "RMSE",
                "seed": 3,
                "eval_metric": "RMSE",
                "explain_level": 2
            },
            "name": "learner_fold_0",
            "best_ntree_limit": 211
        },
        {
            "library_version": "1.2.2",
            "algorithm_name": "CatBoost",
            "algorithm_short_name": "CatBoost",
            "uid": "c878a588-2d50-4832-bd74-4d166a52f665",
            "params": {
                "model_type": "CatBoost",
                "ml_task": "regression",
                "n_jobs": -1,
                "learning_rate": 0.1,
                "depth": 6,
                "rsm": 1,
                "loss_function": "RMSE",
                "seed": 3,
                "eval_metric": "RMSE",
                "explain_level": 2
            },
            "name": "learner_fold_1",
            "best_ntree_limit": 68
        },
        {
            "library_version": "1.2.2",
            "algorithm_name": "CatBoost",
            "algorithm_short_name": "CatBoost",
            "uid": "fb5679fc-0297-45a6-b235-d4c2358d029c",
            "params": {
                "model_type": "CatBoost",
                "ml_task": "regression",
                "n_jobs": -1,
                "learning_rate": 0.1,
                "depth": 6,
                "rsm": 1,
                "loss_function": "RMSE",
                "seed": 3,
                "eval_metric": "RMSE",
                "explain_level": 2
            },
            "name": "learner_fold_2",
            "best_ntree_limit": 175
        },
        {
            "library_version": "1.2.2",
            "algorithm_name": "CatBoost",
            "algorithm_short_name": "CatBoost",
            "uid": "bb389259-9228-4ef7-84a5-afd13c6f44e4",
            "params": {
                "model_type": "CatBoost",
                "ml_task": "regression",
                "n_jobs": -1,
                "learning_rate": 0.1,
                "depth": 6,
                "rsm": 1,
                "loss_function": "RMSE",
                "seed": 3,
                "eval_metric": "RMSE",
                "explain_level": 2
            },
            "name": "learner_fold_3",
            "best_ntree_limit": 178
        },
        {
            "library_version": "1.2.2",
            "algorithm_name": "CatBoost",
            "algorithm_short_name": "CatBoost",
            "uid": "899e8f42-5ad9-413f-ae9d-947b6de2e114",
            "params": {
                "model_type": "CatBoost",
                "ml_task": "regression",
                "n_jobs": -1,
                "learning_rate": 0.1,
                "depth": 6,
                "rsm": 1,
                "loss_function": "RMSE",
                "seed": 3,
                "eval_metric": "RMSE",
                "explain_level": 2
            },
            "name": "learner_fold_4",
            "best_ntree_limit": 133
        },
        {
            "library_version": "1.2.2",
            "algorithm_name": "CatBoost",
            "algorithm_short_name": "CatBoost",
            "uid": "b9a1a7a8-1699-43ab-88b7-c3880ea9b519",
            "params": {
                "model_type": "CatBoost",
                "ml_task": "regression",
                "n_jobs": -1,
                "learning_rate": 0.1,
                "depth": 6,
                "rsm": 1,
                "loss_function": "RMSE",
                "seed": 3,
                "eval_metric": "RMSE",
                "explain_level": 2
            },
            "name": "learner_fold_5",
            "best_ntree_limit": 89
        },
        {
            "library_version": "1.2.2",
            "algorithm_name": "CatBoost",
            "algorithm_short_name": "CatBoost",
            "uid": "8176200f-62e9-46fc-8866-cee55b0ae827",
            "params": {
                "model_type": "CatBoost",
                "ml_task": "regression",
                "n_jobs": -1,
                "learning_rate": 0.1,
                "depth": 6,
                "rsm": 1,
                "loss_function": "RMSE",
                "seed": 3,
                "eval_metric": "RMSE",
                "explain_level": 2
            },
            "name": "learner_fold_6",
            "best_ntree_limit": 71
        },
        {
            "library_version": "1.2.2",
            "algorithm_name": "CatBoost",
            "algorithm_short_name": "CatBoost",
            "uid": "802b36ab-698a-4314-bd37-7e042419d1ca",
            "params": {
                "model_type": "CatBoost",
                "ml_task": "regression",
                "n_jobs": -1,
                "learning_rate": 0.1,
                "depth": 6,
                "rsm": 1,
                "loss_function": "RMSE",
                "seed": 3,
                "eval_metric": "RMSE",
                "explain_level": 2
            },
            "name": "learner_fold_7",
            "best_ntree_limit": 314
        },
        {
            "library_version": "1.2.2",
            "algorithm_name": "CatBoost",
            "algorithm_short_name": "CatBoost",
            "uid": "85c01505-3940-40a2-bd0e-004038726269",
            "params": {
                "model_type": "CatBoost",
                "ml_task": "regression",
                "n_jobs": -1,
                "learning_rate": 0.1,
                "depth": 6,
                "rsm": 1,
                "loss_function": "RMSE",
                "seed": 3,
                "eval_metric": "RMSE",
                "explain_level": 2
            },
            "name": "learner_fold_8",
            "best_ntree_limit": 52
        },
        {
            "library_version": "1.2.2",
            "algorithm_name": "CatBoost",
            "algorithm_short_name": "CatBoost",
            "uid": "0ab28681-7345-44ae-a21c-79d8bd5adbd0",
            "params": {
                "model_type": "CatBoost",
                "ml_task": "regression",
                "n_jobs": -1,
                "learning_rate": 0.1,
                "depth": 6,
                "rsm": 1,
                "loss_function": "RMSE",
                "seed": 3,
                "eval_metric": "RMSE",
                "explain_level": 2
            },
            "name": "learner_fold_9",
            "best_ntree_limit": 141
        }
    ],
    "params": {
        "additional": {
            "max_rounds": 10000,
            "early_stopping_rounds": 50,
            "max_rows_limit": null,
            "max_cols_limit": null
        },
        "preprocessing": {
            "columns_preprocessing": {},
            "target_preprocessing": [
                "na_exclude",
                "scale_normal"
            ],
            "ml_task": "regression"
        },
        "validation_strategy": {
            "validation_type": "kfold",
            "shuffle": true,
            "X_path": "../Model/AutoML_rmse_best_log1p/X.data",
            "y_path": "../Model/AutoML_rmse_best_log1p/y.data",
            "results_path": "../Model/AutoML_rmse_best_log1p/",
            "k_folds": 10
        },
        "learner": {
            "model_type": "CatBoost",
            "ml_task": "regression",
            "n_jobs": -1,
            "learning_rate": 0.1,
            "depth": 6,
            "rsm": 1,
            "loss_function": "RMSE",
            "seed": 3,
            "eval_metric": "RMSE",
            "explain_level": 2
        },
        "automl_random_state": 1234,
        "ml_task": "regression",
        "explain_level": 2,
        "name": "3_Default_CatBoost",
        "status": "initialized",
        "final_loss": null,
        "train_time": null,
        "data_type": "original",
        "max_time_for_learner": 432.0
    },
    "saved": [
        "3_Default_CatBoost\\learner_fold_0.catboost",
        "3_Default_CatBoost\\learner_fold_1.catboost",
        "3_Default_CatBoost\\learner_fold_2.catboost",
        "3_Default_CatBoost\\learner_fold_3.catboost",
        "3_Default_CatBoost\\learner_fold_4.catboost",
        "3_Default_CatBoost\\learner_fold_5.catboost",
        "3_Default_CatBoost\\learner_fold_6.catboost",
        "3_Default_CatBoost\\learner_fold_7.catboost",
        "3_Default_CatBoost\\learner_fold_8.catboost",
        "3_Default_CatBoost\\learner_fold_9.catboost"
    ],
    "predictions_fname": "3_Default_CatBoost\\predictions_out_of_folds.csv",
    "metric_name": "rmse",
    "final_loss": "0.4449725468429141",
    "train_time": 145.04657888412476,
    "is_stacked": false,
    "joblib_version": "1.2.0"
}